minetcookies/__about__.py
minetcookies/__init__.py
minetcookies/main.py
minetcookies-0.3.10.dist-info/METADATA
minetcookies-0.3.10.dist-info/WHEEL
minetcookies-0.3.10.dist-info/entry_points.txt
minetcookies-0.3.10.dist-info/licenses/LICENSE.txt
minetcookies-0.3.10.dist-info/RECORD
