Metadata-Version: 2.1
Name: minetcookies
Version: 0.3.10
Summary: A simple cookie manager for Minet by Medialab
Project-URL: Documentation, https://github.com/Marceau-h/minetcookies#readme
Project-URL: Issues, https://github.com/Marceau-h/minetcookies/issues
Project-URL: Source, https://github.com/Marceau-h/minetcookies
Author-email: Marceau-h <106751184+Marceau-h@users.noreply.github.com>
Maintainer-email: Marceau-h <106751184+Marceau-h@users.noreply.github.com>
License-Expression: AGPL-3.0-or-later
License-File: LICENSE.txt
Keywords: cookie,cookies,manager,minet,minet-cookies,minetcookies
Classifier: Development Status :: 4 - Beta
Classifier: License :: OSI Approved :: GNU Affero General Public License v3 or later (AGPLv3+)
Classifier: Operating System :: OS Independent
Classifier: Programming Language :: Python
Classifier: Programming Language :: Python :: 3.7
Classifier: Programming Language :: Python :: 3.8
Classifier: Programming Language :: Python :: 3.9
Classifier: Programming Language :: Python :: 3.10
Classifier: Programming Language :: Python :: 3.11
Classifier: Programming Language :: Python :: Implementation :: CPython
Classifier: Programming Language :: Python :: Implementation :: PyPy
Requires-Python: >=3.7
Requires-Dist: minet~=0.67.1
Requires-Dist: pyyaml~=6.0
Requires-Dist: tqdm~=2.2.0
